bold_retriever-0.2.2.dist-info/RECORD
bold_retriever-0.2.2.dist-info/WHEEL
bold_retriever-0.2.2.dist-info/METADATA
bold_retriever-0.2.2.dist-info/top_level.txt
bold_retriever-0.2.2.dist-info/metadata.json
bold_retriever-0.2.2.dist-info/DESCRIPTION.rst
bold_retriever/__init__.py
bold_retriever/bold_retriever.py
