Metadata-Version: 2.0
Name: bold-retriever
Version: 0.2.2
Summary: It queries the BOLD database to get identification of taxa based on COI sequences
Home-page: https://github.com/carlosp420/bold_retriever
Author: Carlos Pena
Author-email: mycalesis@gmail.com
License: GPL v3
Keywords: bold_retriever
Platform: UNKNOWN
Classifier: Development Status :: 2 - Pre-Alpha
Classifier: Programming Language :: Python
Classifier: Topic :: Scientific/Engineering :: Bio-Informatics
Classifier: Intended Audience :: Science/Research
Classifier: License :: OSI Approved :: GNU General Public License v3 (GPLv3)
Classifier: Natural Language :: English
Classifier: Environment :: Console
Classifier: Programming Language :: Python :: 2.7
